MANIFEST.in
README.txt
setup.cfg
setup.py
csci/__init__.py
csci.feedback.egg-info/PKG-INFO
csci.feedback.egg-info/SOURCES.txt
csci.feedback.egg-info/dependency_links.txt
csci.feedback.egg-info/entry_points.txt
csci.feedback.egg-info/namespace_packages.txt
csci.feedback.egg-info/not-zip-safe
csci.feedback.egg-info/paster_plugins.txt
csci.feedback.egg-info/requires.txt
csci.feedback.egg-info/top_level.txt
csci/feedback/README.txt
csci/feedback/__init__.py
csci/feedback/config.py
csci/feedback/configure.zcml
csci/feedback/browser/__init__.py
csci/feedback/browser/configure.zcml
csci/feedback/browser/fbformview.pt
csci/feedback/browser/fbformview.py
csci/feedback/browser/feedback.py
csci/feedback/content/__init__.py
csci/feedback/content/configure.zcml
csci/feedback/interfaces/__init__.py
csci/feedback/portlets/__init__.py
csci/feedback/portlets/configure.zcml
csci/feedback/profiles/default/factorytool.xml
csci/feedback/profiles/default/metadata.xml
csci/feedback/profiles/default/portlets.xml
csci/feedback/profiles/default/types.xml
csci/feedback/tests/__init__.py
csci/feedback/tests/base.py
csci/feedback/tests/test_doctest.py