Metadata-Version: 1.0
Name: csci.feedback
Version: 1.1
Summary: Feedback forms
Home-page: http://svn.plone.org/svn/plone/plone.example
Author: Peter Dyson
Author-email: pdyson@cannonscientific.com
License: GPL
Keywords: feedback form
Platform: UNKNOWN
Classifier: Framework :: Plone
Classifier: Intended Audience :: Developers
Classifier: License :: OSI Approved :: GNU General Public License (GPL)
